rtl/Ram.v
module Ram (
    input  wire        clk,
    input  wire        memRead,
    input  wire        memWrite,
    input  wire [5:0]  addr,
    input  wire [15:0] writeData,
    output reg  [15:0] readData
);

    reg [15:0] memory [0:63];

    // Escrita (SW)
    always @(posedge clk) begin
        if (memWrite)
            memory[addr] <= writeData;
    end

    // Leitura (LW)
    always @(*) begin
        if (memRead)
            readData = memory[addr];
        else
            readData = 16'b0;
    end

endmodule

rtl/SomadorSubtrator.v
module SomadorSubtrator (
    input  wire [15:0] a,
    input  wire [15:0] b,
    input  wire        sub,  
    output reg  [15:0] s,
    output reg         Cout
);

    reg [16:0] temp;

    always @(*) begin
        case (sub)
            1'b0: begin
                temp = a + b;
                s    = temp[15:0];
                Cout = temp[16];   // carry-out
            end

            1'b1: begin
                temp = a - b;
                s    = temp[15:0];
                Cout = ~temp[16];  // borrow invertido
            end

            default: begin
                s    = 16'b0;
                Cout = 1'b0;
            end
        endcase
    end

endmodule

rtl/Ula.v
module Ula (
    input  wire [15:0] a,
    input  wire [15:0] b,
    input  wire [2:0]  select,
    output reg  [15:0] aluResult,
    output wire Cout
);

    wire [15:0] somaSub;
    wire sub;


    assign sub = (select == 3'b001);

    SomadorSubtrator somador (
        .a(a),
        .b(b),
        .sub(sub),
        .s(somaSub),
        .Cout(Cout)
    );

    always @(*) begin
        case (select)
            3'b000: aluResult = somaSub;        // Soma
            3'b001: aluResult = somaSub;        // Subtração
            3'b010: aluResult = a & b;           // AND
            3'b011: aluResult = a | b;           // OR
            3'b100: aluResult = ~(a & b);        // NAND
            3'b101: aluResult = ~(a | b);        // NOR
            3'b110: aluResult = a ^ b;           // XOR
            3'b111: aluResult = ~(Cout == 1'b0) ? 16'h0000 : 16'h0001;
            default: aluResult = 16'b0;
        endcase
    end

endmodule

rtl/registradores.v
module registradores (
    input  wire        clk,
    input  wire        reset,   
    input  wire        regWrite,
    input  wire [2:0]  readReg1,
    input  wire [2:0]  readReg2,
    input  wire [2:0]  writeReg,
    input  wire [15:0] writeData,
    output wire [15:0] readData1,
    output wire [15:0] readData2
);

    reg [15:0] regs [0:7];
    integer i;

    assign readData1 = (readReg1 == 3'd0) ? 16'b0 : regs[readReg1];
    assign readData2 = (readReg2 == 3'd0) ? 16'b0 : regs[readReg2];

    always @(posedge clk or posedge reset) begin
        if (reset) begin
            for (i = 0; i < 8; i = i + 1)
                regs[i] <= 16'b0;
        end
        else if (regWrite && writeReg != 3'd0) begin
            regs[writeReg] <= writeData;
        end
    end

endmodule

rtl/aluControl.v
module aluControl (
    input  wire [2:0] funct,
    input  wire [3:0] AluOp,
    output wire [2:0] S
);

    assign S = (AluOp[3]) ? AluOp[2:0] : funct;

endmodule

rtl/control.v
module control (
    input  wire [3:0] opCode,

    output reg  regDst,
    output reg  jump,
    output reg  branch,
    output reg  memRead,
    output reg  memToReg,
    output reg  [3:0] aluOp,
    output reg  memWrite,
    output reg  aluSrc,
    output reg  regWrite,
    output reg  halt
);

always @(*) begin
    // ===== DEFAULTS (SEM LATCH!) =====
    regDst   = 0;
    jump     = 0;
    branch   = 0;
    memRead  = 0;
    memToReg = 0;
    aluOp    = 4'b0000;
    memWrite = 0;
    aluSrc   = 0;
    regWrite = 0;
    halt     = 0;

    case (opCode)

        // ===== TIPO R =====
        4'b0000: begin
            regDst   = 1;
            regWrite = 1;
            aluOp    = 4'b0000;
        end

        // ===== LW =====
        4'b0001: begin
            memRead  = 1;   // 👈 SÓ AQUI
            memToReg = 1;
            aluSrc   = 1;
            regWrite = 1;
            aluOp    = 4'b1000;
        end

        // ===== BEQ =====
        4'b0010: begin
            branch = 1;
            aluOp  = 4'b1001;
        end

        // ===== ORi =====
        4'b0011: begin
            aluSrc   = 1;
            regWrite = 1;
            aluOp    = 4'b1011;
        end

        // ===== SW =====
        4'b0100: begin
            memWrite = 1;
            aluSrc   = 1;
            aluOp    = 4'b1000;
        end

        // ===== ANDi =====
        4'b0101: begin
            aluSrc   = 1;
            regWrite = 1;
            aluOp    = 4'b1010;
        end

        // ===== ADDi =====
        4'b0110: begin
            aluSrc   = 1;
            regWrite = 1;
            aluOp    = 4'b1000;
        end

        // ===== SLTi =====
        4'b0111: begin
            aluSrc   = 1;
            regWrite = 1;
            aluOp    = 4'b1111;
        end

        // ===== JUMP =====
        4'b1000: begin
            jump = 1;
        end

        // ===== HALT =====
        4'b1111: begin
            halt = 1;
        end

    endcase
end

endmodule

rtl/Rom.v
module Rom (
    input  wire [5:0]  addr,      // PC[7:0] (256 instruções)
    output wire [15:0] instr
);

    reg [15:0] memory [0:63];

    // Inicializa programa
    integer i;

    initial begin
        // Inicializa tudo com 0
        for (i = 0; i < 64; i = i + 1)
            memory[i] = 16'b0;

        // Depois carrega o programa
        $readmemb("program.mem", memory);
    end
    
    assign instr = memory[addr];

endmodule

rtl/Pc.v
module Pc (
    input  wire        clk,
    input  wire        reset,
    input  wire        halt,
    input  wire        branch,
    input  wire        zero,
    input  wire        jump,
    input  wire [5:0]  immBranch,
    input  wire [5:0]  jumpAddr,
    output reg  [5:0]  pc
);

    wire [5:0] pcMais1;
    wire [5:0] branchTrue;
    wire [5:0] pcAfterBranch;
    wire [5:0] nextPc;

    // Incremento normal
    assign pcMais1 = pc + 6'd1;

    // Branch destino
    assign branchTrue = pcMais1 + immBranch;

    // Decide branch
    assign pcAfterBranch = (branch & zero) ? branchTrue : pcMais1;

    // Jump tem prioridade maior
    assign nextPc = jump ? jumpAddr : pcAfterBranch;

    // Registrador do PC
    always @(posedge clk or posedge reset) begin
        if (reset)
            pc <= 6'd0;
        else if (!halt)
            pc <= nextPc;
    end

endmodule

rtl/Cpu.v
module Cpu (
    input wire clk,
    input wire reset
);

    // =====================
    // FIOS INTERNOS
    // =====================

    wire [5:0] pc;
    wire [15:0] instruction;

    wire regDst, jump, branch, memRead;
    wire memToReg, memWrite, aluSrc, regWrite, halt;
    wire [3:0] aluOp;

    wire [2:0] aluSelect;

    wire [15:0] readData1, readData2;
    wire [15:0] aluResult;
    wire [15:0] ramReadData;

    wire zero;
    assign zero = (aluResult == 16'b0);

    // =====================
    // PC
    // =====================

    Pc pc_unit (
        .clk(clk),
        .reset(reset),
        .halt(halt),        // 👈 mantém isso
        .branch(branch),
        .zero(zero),
        .jump(jump),
        .immBranch(instruction[5:0]),
        .jumpAddr(instruction[5:0]),
        .pc(pc)
    );

    // =====================
    // ROM
    // =====================

    Rom rom_unit (
        .addr(pc),
        .instr(instruction)
    );

    // =====================
    // CONTROL
    // =====================

    control control_unit (
        .opCode(instruction[15:12]),
        .regDst(regDst),
        .jump(jump),
        .branch(branch),
        .memRead(memRead),
        .memToReg(memToReg),
        .aluOp(aluOp),
        .memWrite(memWrite),
        .aluSrc(aluSrc),
        .regWrite(regWrite),
        .halt(halt)
    );

    // =====================
    // ALU CONTROL
    // =====================

    aluControl alu_ctrl (
        .funct(instruction[2:0]),
        .AluOp(aluOp),
        .S(aluSelect)
    );

    // =====================
    // REGISTER FILE
    // =====================

    wire [2:0] writeReg;

    assign writeReg = regDst ? instruction[5:3]
                             : instruction[8:6];

    wire [15:0] writeData;

    assign writeData = memToReg ? ramReadData
                                : aluResult;

    registradores reg_file (
        .clk(clk),
        .reset(reset),          // 🔥 ADICIONADO
        .regWrite(regWrite),
        .readReg1(instruction[11:9]),
        .readReg2(instruction[8:6]),
        .writeReg(writeReg),
        .writeData(writeData),
        .readData1(readData1),
        .readData2(readData2)
    );

    // =====================
    // ALU
    // =====================

    wire [15:0] aluB;

    // 🔥 EXTENSÃO DE SINAL PARA IMEDIATO 6 BITS
    wire [15:0] immExt;
    assign immExt = {{10{instruction[5]}}, instruction[5:0]};

    assign aluB = aluSrc ? immExt
                         : readData2;

    Ula alu_unit (
        .a(readData1),
        .b(aluB),
        .select(aluSelect),
        .aluResult(aluResult),
        .Cout()
    );

    // =====================
    // RAM
    // =====================

    Ram ram_unit (
        .clk(clk),
        .memRead(memRead),
        .memWrite(memWrite),
        .addr(aluResult[5:0]),
        .writeData(readData2),
        .readData(ramReadData)
    );

endmodule

sim/CpuTest.v
`timescale 1ns/1ps

module Cpu_tb;

    // Sinais de teste
    reg clk;
    reg reset;

    // Instancia a CPU
    Cpu uut (
        .clk(clk),
        .reset(reset)
    );

    // ===== GERAÇÃO DO CLOCK =====
    initial begin
        clk = 0;
        forever #5 clk = ~clk;  // Clock de 10ns
    end

    // ===== SEQUÊNCIA DE TESTE =====
    initial begin
        $display("Iniciando simulação...");
        $dumpfile("cpu.vcd");   // Para GTKWave
        $dumpvars(0, Cpu_tb);

        // Reset inicial
        reset = 1;
        #20;

        reset = 0;

        // Deixa rodar por vários ciclos
        #500;

        $display("=================================");
        $display("Fibonacci(10) = %d", uut.reg_file.regs[4]);
        $display("=================================");
        $display("Finalizando simulação.");
        $finish;
    end

endmodule

cpu.vcd
$date
	Fri Feb 20 00:25:23 2026
$end
$version
	Icarus Verilog
$end
$timescale
	1ps
$end
$scope module Cpu_tb $end
$var reg 1 ! clk $end
$var reg 1 " reset $end
$scope module uut $end
$var wire 1 ! clk $end
$var wire 1 " reset $end
$var wire 1 # zero $end
$var wire 3 $ writeReg [2:0] $end
$var wire 16 % writeData [15:0] $end
$var wire 1 & regWrite $end
$var wire 1 ' regDst $end
$var wire 16 ( readData2 [15:0] $end
$var wire 16 ) readData1 [15:0] $end
$var wire 16 * ramReadData [15:0] $end
$var wire 6 + pc [5:0] $end
$var wire 1 , memWrite $end
$var wire 1 - memToReg $end
$var wire 1 . memRead $end
$var wire 1 / jump $end
$var wire 16 0 instruction [15:0] $end
$var wire 16 1 immExt [15:0] $end
$var wire 1 2 halt $end
$var wire 1 3 branch $end
$var wire 1 4 aluSrc $end
$var wire 3 5 aluSelect [2:0] $end
$var wire 16 6 aluResult [15:0] $end
$var wire 4 7 aluOp [3:0] $end
$var wire 16 8 aluB [15:0] $end
$scope module alu_ctrl $end
$var wire 3 9 funct [2:0] $end
$var wire 3 : S [2:0] $end
$var wire 4 ; AluOp [3:0] $end
$upscope $end
$scope module alu_unit $end
$var wire 16 < b [15:0] $end
$var wire 3 = select [2:0] $end
$var wire 1 > sub $end
$var wire 16 ? somaSub [15:0] $end
$var wire 16 @ a [15:0] $end
$var wire 1 A Cout $end
$var reg 16 B aluResult [15:0] $end
$scope module somador $end
$var wire 16 C b [15:0] $end
$var wire 1 > sub $end
$var wire 16 D a [15:0] $end
$var reg 1 A Cout $end
$var reg 16 E s [15:0] $end
$var reg 17 F temp [16:0] $end
$upscope $end
$upscope $end
$scope module control_unit $end
$var wire 4 G opCode [3:0] $end
$var reg 4 H aluOp [3:0] $end
$var reg 1 4 aluSrc $end
$var reg 1 3 branch $end
$var reg 1 2 halt $end
$var reg 1 / jump $end
$var reg 1 . memRead $end
$var reg 1 - memToReg $end
$var reg 1 , memWrite $end
$var reg 1 ' regDst $end
$var reg 1 & regWrite $end
$upscope $end
$scope module pc_unit $end
$var wire 1 3 branch $end
$var wire 1 ! clk $end
$var wire 1 2 halt $end
$var wire 6 I immBranch [5:0] $end
$var wire 1 / jump $end
$var wire 6 J jumpAddr [5:0] $end
$var wire 1 " reset $end
$var wire 1 # zero $end
$var wire 6 K pcMais1 [5:0] $end
$var wire 6 L pcAfterBranch [5:0] $end
$var wire 6 M nextPc [5:0] $end
$var wire 6 N branchTrue [5:0] $end
$var reg 6 O pc [5:0] $end
$upscope $end
$scope module ram_unit $end
$var wire 6 P addr [5:0] $end
$var wire 1 ! clk $end
$var wire 1 . memRead $end
$var wire 1 , memWrite $end
$var wire 16 Q writeData [15:0] $end
$var reg 16 R readData [15:0] $end
$upscope $end
$scope module reg_file $end
$var wire 1 ! clk $end
$var wire 3 S readReg1 [2:0] $end
$var wire 3 T readReg2 [2:0] $end
$var wire 1 & regWrite $end
$var wire 1 " reset $end
$var wire 16 U writeData [15:0] $end
$var wire 3 V writeReg [2:0] $end
$var wire 16 W readData2 [15:0] $end
$var wire 16 X readData1 [15:0] $end
$var integer 32 Y i [31:0] $end
$upscope $end
$scope module rom_unit $end
$var wire 6 Z addr [5:0] $end
$var wire 16 [ instr [15:0] $end
$var integer 32 \ i [31:0] $end
$upscope $end
$upscope $end
$upscope $end
$enddefinitions $end
$comment Show the parameter values. $end
$dumpall
$end
#0
$dumpvars
b1000000 \
b110001000000001 [
b0 Z
b1000 Y
b0 X
b0 W
b0 V
b1 U
b0 T
b1 S
b0 R
b0 Q
b1 P
b0 O
b10 N
b1 M
b1 L
b1 K
b1 J
b1 I
b1000 H
b110 G
b1 F
b1 E
b0 D
b1 C
b1 B
0A
b0 @
b1 ?
0>
b0 =
b1 <
b1000 ;
b0 :
b1 9
b1 8
b1000 7
b1 6
b0 5
14
03
02
b1 1
b110001000000001 0
0/
0.
0-
0,
b0 +
b0 *
b0 )
b0 (
0'
1&
b1 %
b0 $
0#
1"
0!
$end
#5000
b1000 Y
1!
#10000
0!
#15000
b1000 Y
1!
#20000
0!
0"
#25000
b0 P
b0 %
b0 U
1#
b0 6
b0 B
b0 ?
b0 E
b0 F
b10 M
b0 8
b0 <
b0 C
b10 L
b0 1
b10 S
b0 9
b0 J
b0 I
b10 N
b10 K
b110010000000000 0
b110010000000000 [
b1 +
b1 O
b1 Z
1!
#30000
0!
#35000
b1010 P
b1010 %
b1010 U
0#
b1010 6
b1010 B
b1010 ?
b1010 E
b1010 F
b11 M
b1010 8
b1010 <
b1010 C
b11 L
b1010 1
b11 S
b10 9
b1010 J
b1010 I
b1101 N
b11 K
b110011000001010 0
b110011000001010 [
b10 +
b10 O
b10 Z
1!
#40000
0!
#45000
b0 P
b0 %
b0 U
1#
b0 6
b0 B
b0 ?
b0 E
b0 F
b100 M
b0 8
b0 <
b0 C
b100 $
b100 V
1'
1&
04
b0 7
b0 ;
b0 H
b100 L
b1111111111100000 1
b10 T
b10 S
b0 9
b0 G
b100000 J
b100000 I
b100100 N
b100 K
b10010100000 0
b10010100000 [
b11 +
b11 O
b11 Z
1!
#50000
0!
#55000
b101 M
b10 $
b10 V
b1000 7
b1000 ;
b1000 H
14
1&
0'
b101 L
b0 1
b100 S
b110 G
b0 J
b0 I
b101 N
b101 K
b110100010000000 0
b110100010000000 [
b100 +
b100 O
b100 Z
1!
#60000
0!
#65000
b110 M
b110 L
b1 S
b110 N
b110 K
b110001010000000 0
b110001010000000 [
b101 +
b101 O
b101 Z
1!
#70000
0!
#75000
b111111 P
b1111111111111111 %
b1111111111111111 U
0#
b1111111111111111 6
b1111111111111111 B
b1111111111111111 ?
b1111111111111111 E
b1111111111111111 F
b111 M
b1111111111111111 8
b1111111111111111 <
b1111111111111111 C
b11 $
b11 V
b111 L
b1111111111111111 1
b11 T
b11 S
b111 9
b111111 J
b111111 I
b110 N
b111 K
b110011011111111 0
b110011011111111 [
b110 +
b110 O
b110 Z
1!
#80000
0!
#85000
1A
1>
b1 5
b1 :
b1 =
b1000 M
b0 8
b0 <
b0 C
b0 $
b0 V
13
0&
04
b1001 7
b1001 ;
b1001 H
b1111111111111111 )
b1111111111111111 @
b1111111111111111 D
b1111111111111111 X
b1000 L
b10 1
b0 T
b10 9
b10 G
b10 J
b10 I
b1010 N
b1000 K
b10011000000010 0
b10011000000010 [
b111 +
b111 O
b111 Z
1!
#90000
0!
#95000
0A
b0 P
b0 %
b0 U
0>
b11 5
b11 :
b11 =
1#
b0 6
b0 B
b0 ?
b0 E
b0 F
b11 M
b0 )
b0 @
b0 D
b0 X
1/
b0 7
b0 ;
b0 H
03
b1001 L
b11 1
b0 S
b11 9
b1000 G
b11 J
b11 I
b1100 N
b1001 K
b1000000000000011 0
b1000000000000011 [
b1000 +
b1000 O
b1000 Z
1!
#100000
0!
#105000
b100 $
b100 V
b0 5
b0 :
b0 =
1&
1'
0/
b100 M
b100 L
b1111111111100000 1
b10 T
b10 S
b0 9
b0 G
b100000 J
b100000 I
b100100 N
b100 K
b10010100000 0
b10010100000 [
b11 +
b11 O
b11 Z
1!
#110000
0!
#115000
b101 M
b10 $
b10 V
b1000 7
b1000 ;
b1000 H
14
1&
0'
b101 L
b0 1
b100 S
b110 G
b0 J
b0 I
b101 N
b101 K
b110100010000000 0
b110100010000000 [
b100 +
b100 O
b100 Z
1!
#120000
0!
#125000
b110 M
b110 L
b1 S
b110 N
b110 K
b110001010000000 0
b110001010000000 [
b101 +
b101 O
b101 Z
1!
#130000
0!
#135000
b111110 P
b1111111111111110 %
b1111111111111110 U
0#
b1111111111111110 6
b1111111111111110 B
1A
b1111111111111110 ?
b1111111111111110 E
b11111111111111110 F
b111 M
b1111111111111111 8
b1111111111111111 <
b1111111111111111 C
b1111111111111111 (
b1111111111111111 Q
b1111111111111111 W
b1111111111111111 )
b1111111111111111 @
b1111111111111111 D
b1111111111111111 X
b11 $
b11 V
b111 L
b1111111111111111 1
b11 T
b11 S
b111 9
b111111 J
b111111 I
b110 N
b111 K
b110011011111111 0
b110011011111111 [
b110 +
b110 O
b110 Z
1!
#140000
0!
#145000
1>
b1 5
b1 :
b1 =
1A
b1111111111111110 F
b1000 M
b0 8
b0 <
b0 C
b0 $
b0 V
13
0&
04
b1001 7
b1001 ;
b1001 H
b1111111111111110 )
b1111111111111110 @
b1111111111111110 D
b1111111111111110 X
b0 (
b0 Q
b0 W
b1000 L
b10 1
b0 T
b10 9
b10 G
b10 J
b10 I
b1010 N
b1000 K
b10011000000010 0
b10011000000010 [
b111 +
b111 O
b111 Z
1!
#150000
0!
#155000
0A
b0 P
b0 %
b0 U
0>
b11 5
b11 :
b11 =
1#
b0 6
b0 B
b0 ?
b0 E
b0 F
b11 M
b0 )
b0 @
b0 D
b0 X
1/
b0 7
b0 ;
b0 H
03
b1001 L
b11 1
b0 S
b11 9
b1000 G
b11 J
b11 I
b1100 N
b1001 K
b1000000000000011 0
b1000000000000011 [
b1000 +
b1000 O
b1000 Z
1!
#160000
0!
#165000
b100 $
b100 V
b0 5
b0 :
b0 =
1&
1'
0/
b100 M
b100 L
b1111111111100000 1
b10 T
b10 S
b0 9
b0 G
b100000 J
b100000 I
b100100 N
b100 K
b10010100000 0
b10010100000 [
b11 +
b11 O
b11 Z
1!
#170000
0!
#175000
b101 M
b10 $
b10 V
b1000 7
b1000 ;
b1000 H
14
1&
0'
b101 L
b0 1
b100 S
b110 G
b0 J
b0 I
b101 N
b101 K
b110100010000000 0
b110100010000000 [
b100 +
b100 O
b100 Z
1!
#180000
0!
#185000
b110 M
b110 L
b1 S
b110 N
b110 K
b110001010000000 0
b110001010000000 [
b101 +
b101 O
b101 Z
1!
#190000
0!
#195000
b111101 P
b1111111111111101 %
b1111111111111101 U
0#
b1111111111111101 6
b1111111111111101 B
1A
b1111111111111101 ?
b1111111111111101 E
b11111111111111101 F
b111 M
b1111111111111111 8
b1111111111111111 <
b1111111111111111 C
b1111111111111110 (
b1111111111111110 Q
b1111111111111110 W
b1111111111111110 )
b1111111111111110 @
b1111111111111110 D
b1111111111111110 X
b11 $
b11 V
b111 L
b1111111111111111 1
b11 T
b11 S
b111 9
b111111 J
b111111 I
b110 N
b111 K
b110011011111111 0
b110011011111111 [
b110 +
b110 O
b110 Z
1!
#200000
0!
#205000
1>
b1 5
b1 :
b1 =
1A
b1111111111111101 F
b1000 M
b0 8
b0 <
b0 C
b0 $
b0 V
13
0&
04
b1001 7
b1001 ;
b1001 H
b1111111111111101 )
b1111111111111101 @
b1111111111111101 D
b1111111111111101 X
b0 (
b0 Q
b0 W
b1000 L
b10 1
b0 T
b10 9
b10 G
b10 J
b10 I
b1010 N
b1000 K
b10011000000010 0
b10011000000010 [
b111 +
b111 O
b111 Z
1!
#210000
0!
#215000
0A
b0 P
b0 %
b0 U
0>
b11 5
b11 :
b11 =
1#
b0 6
b0 B
b0 ?
b0 E
b0 F
b11 M
b0 )
b0 @
b0 D
b0 X
1/
b0 7
b0 ;
b0 H
03
b1001 L
b11 1
b0 S
b11 9
b1000 G
b11 J
b11 I
b1100 N
b1001 K
b1000000000000011 0
b1000000000000011 [
b1000 +
b1000 O
b1000 Z
1!
#220000
0!
#225000
b100 $
b100 V
b0 5
b0 :
b0 =
1&
1'
0/
b100 M
b100 L
b1111111111100000 1
b10 T
b10 S
b0 9
b0 G
b100000 J
b100000 I
b100100 N
b100 K
b10010100000 0
b10010100000 [
b11 +
b11 O
b11 Z
1!
#230000
0!
#235000
b101 M
b10 $
b10 V
b1000 7
b1000 ;
b1000 H
14
1&
0'
b101 L
b0 1
b100 S
b110 G
b0 J
b0 I
b101 N
b101 K
b110100010000000 0
b110100010000000 [
b100 +
b100 O
b100 Z
1!
#240000
0!
#245000
b110 M
b110 L
b1 S
b110 N
b110 K
b110001010000000 0
b110001010000000 [
b101 +
b101 O
b101 Z
1!
#250000
0!
#255000
b111100 P
b1111111111111100 %
b1111111111111100 U
0#
b1111111111111100 6
b1111111111111100 B
1A
b1111111111111100 ?
b1111111111111100 E
b11111111111111100 F
b111 M
b1111111111111111 8
b1111111111111111 <
b1111111111111111 C
b1111111111111101 (
b1111111111111101 Q
b1111111111111101 W
b1111111111111101 )
b1111111111111101 @
b1111111111111101 D
b1111111111111101 X
b11 $
b11 V
b111 L
b1111111111111111 1
b11 T
b11 S
b111 9
b111111 J
b111111 I
b110 N
b111 K
b110011011111111 0
b110011011111111 [
b110 +
b110 O
b110 Z
1!
#260000
0!
#265000
1>
b1 5
b1 :
b1 =
1A
b1111111111111100 F
b1000 M
b0 8
b0 <
b0 C
b0 $
b0 V
13
0&
04
b1001 7
b1001 ;
b1001 H
b1111111111111100 )
b1111111111111100 @
b1111111111111100 D
b1111111111111100 X
b0 (
b0 Q
b0 W
b1000 L
b10 1
b0 T
b10 9
b10 G
b10 J
b10 I
b1010 N
b1000 K
b10011000000010 0
b10011000000010 [
b111 +
b111 O
b111 Z
1!
#270000
0!
#275000
0A
b0 P
b0 %
b0 U
0>
b11 5
b11 :
b11 =
1#
b0 6
b0 B
b0 ?
b0 E
b0 F
b11 M
b0 )
b0 @
b0 D
b0 X
1/
b0 7
b0 ;
b0 H
03
b1001 L
b11 1
b0 S
b11 9
b1000 G
b11 J
b11 I
b1100 N
b1001 K
b1000000000000011 0
b1000000000000011 [
b1000 +
b1000 O
b1000 Z
1!
#280000
0!
#285000
b100 $
b100 V
b0 5
b0 :
b0 =
1&
1'
0/
b100 M
b100 L
b1111111111100000 1
b10 T
b10 S
b0 9
b0 G
b100000 J
b100000 I
b100100 N
b100 K
b10010100000 0
b10010100000 [
b11 +
b11 O
b11 Z
1!
#290000
0!
#295000
b101 M
b10 $
b10 V
b1000 7
b1000 ;
b1000 H
14
1&
0'
b101 L
b0 1
b100 S
b110 G
b0 J
b0 I
b101 N
b101 K
b110100010000000 0
b110100010000000 [
b100 +
b100 O
b100 Z
1!
#300000
0!
#305000
b110 M
b110 L
b1 S
b110 N
b110 K
b110001010000000 0
b110001010000000 [
b101 +
b101 O
b101 Z
1!
#310000
0!
#315000
b111011 P
b1111111111111011 %
b1111111111111011 U
0#
b1111111111111011 6
b1111111111111011 B
1A
b1111111111111011 ?
b1111111111111011 E
b11111111111111011 F
b111 M
b1111111111111111 8
b1111111111111111 <
b1111111111111111 C
b1111111111111100 (
b1111111111111100 Q
b1111111111111100 W
b1111111111111100 )
b1111111111111100 @
b1111111111111100 D
b1111111111111100 X
b11 $
b11 V
b111 L
b1111111111111111 1
b11 T
b11 S
b111 9
b111111 J
b111111 I
b110 N
b111 K
b110011011111111 0
b110011011111111 [
b110 +
b110 O
b110 Z
1!
#320000
0!
#325000
1>
b1 5
b1 :
b1 =
1A
b1111111111111011 F
b1000 M
b0 8
b0 <
b0 C
b0 $
b0 V
13
0&
04
b1001 7
b1001 ;
b1001 H
b1111111111111011 )
b1111111111111011 @
b1111111111111011 D
b1111111111111011 X
b0 (
b0 Q
b0 W
b1000 L
b10 1
b0 T
b10 9
b10 G
b10 J
b10 I
b1010 N
b1000 K
b10011000000010 0
b10011000000010 [
b111 +
b111 O
b111 Z
1!
#330000
0!
#335000
0A
b0 P
b0 %
b0 U
0>
b11 5
b11 :
b11 =
1#
b0 6
b0 B
b0 ?
b0 E
b0 F
b11 M
b0 )
b0 @
b0 D
b0 X
1/
b0 7
b0 ;
b0 H
03
b1001 L
b11 1
b0 S
b11 9
b1000 G
b11 J
b11 I
b1100 N
b1001 K
b1000000000000011 0
b1000000000000011 [
b1000 +
b1000 O
b1000 Z
1!
#340000
0!
#345000
b100 $
b100 V
b0 5
b0 :
b0 =
1&
1'
0/
b100 M
b100 L
b1111111111100000 1
b10 T
b10 S
b0 9
b0 G
b100000 J
b100000 I
b100100 N
b100 K
b10010100000 0
b10010100000 [
b11 +
b11 O
b11 Z
1!
#350000
0!
#355000
b101 M
b10 $
b10 V
b1000 7
b1000 ;
b1000 H
14
1&
0'
b101 L
b0 1
b100 S
b110 G
b0 J
b0 I
b101 N
b101 K
b110100010000000 0
b110100010000000 [
b100 +
b100 O
b100 Z
1!
#360000
0!
#365000
b110 M
b110 L
b1 S
b110 N
b110 K
b110001010000000 0
b110001010000000 [
b101 +
b101 O
b101 Z
1!
#370000
0!
#375000
b111010 P
b1111111111111010 %
b1111111111111010 U
0#
b1111111111111010 6
b1111111111111010 B
1A
b1111111111111010 ?
b1111111111111010 E
b11111111111111010 F
b111 M
b1111111111111111 8
b1111111111111111 <
b1111111111111111 C
b1111111111111011 (
b1111111111111011 Q
b1111111111111011 W
b1111111111111011 )
b1111111111111011 @
b1111111111111011 D
b1111111111111011 X
b11 $
b11 V
b111 L
b1111111111111111 1
b11 T
b11 S
b111 9
b111111 J
b111111 I
b110 N
b111 K
b110011011111111 0
b110011011111111 [
b110 +
b110 O
b110 Z
1!
#380000
0!
#385000
1>
b1 5
b1 :
b1 =
1A
b1111111111111010 F
b1000 M
b0 8
b0 <
b0 C
b0 $
b0 V
13
0&
04
b1001 7
b1001 ;
b1001 H
b1111111111111010 )
b1111111111111010 @
b1111111111111010 D
b1111111111111010 X
b0 (
b0 Q
b0 W
b1000 L
b10 1
b0 T
b10 9
b10 G
b10 J
b10 I
b1010 N
b1000 K
b10011000000010 0
b10011000000010 [
b111 +
b111 O
b111 Z
1!
#390000
0!
#395000
0A
b0 P
b0 %
b0 U
0>
b11 5
b11 :
b11 =
1#
b0 6
b0 B
b0 ?
b0 E
b0 F
b11 M
b0 )
b0 @
b0 D
b0 X
1/
b0 7
b0 ;
b0 H
03
b1001 L
b11 1
b0 S
b11 9
b1000 G
b11 J
b11 I
b1100 N
b1001 K
b1000000000000011 0
b1000000000000011 [
b1000 +
b1000 O
b1000 Z
1!
#400000
0!
#405000
b100 $
b100 V
b0 5
b0 :
b0 =
1&
1'
0/
b100 M
b100 L
b1111111111100000 1
b10 T
b10 S
b0 9
b0 G
b100000 J
b100000 I
b100100 N
b100 K
b10010100000 0
b10010100000 [
b11 +
b11 O
b11 Z
1!
#410000
0!
#415000
b101 M
b10 $
b10 V
b1000 7
b1000 ;
b1000 H
14
1&
0'
b101 L
b0 1
b100 S
b110 G
b0 J
b0 I
b101 N
b101 K
b110100010000000 0
b110100010000000 [
b100 +
b100 O
b100 Z
1!
#420000
0!
#425000
b110 M
b110 L
b1 S
b110 N
b110 K
b110001010000000 0
b110001010000000 [
b101 +
b101 O
b101 Z
1!
#430000
0!
#435000
b111001 P
b1111111111111001 %
b1111111111111001 U
0#
b1111111111111001 6
b1111111111111001 B
1A
b1111111111111001 ?
b1111111111111001 E
b11111111111111001 F
b111 M
b1111111111111111 8
b1111111111111111 <
b1111111111111111 C
b1111111111111010 (
b1111111111111010 Q
b1111111111111010 W
b1111111111111010 )
b1111111111111010 @
b1111111111111010 D
b1111111111111010 X
b11 $
b11 V
b111 L
b1111111111111111 1
b11 T
b11 S
b111 9
b111111 J
b111111 I
b110 N
b111 K
b110011011111111 0
b110011011111111 [
b110 +
b110 O
b110 Z
1!
#440000
0!
#445000
1>
b1 5
b1 :
b1 =
1A
b1111111111111001 F
b1000 M
b0 8
b0 <
b0 C
b0 $
b0 V
13
0&
04
b1001 7
b1001 ;
b1001 H
b1111111111111001 )
b1111111111111001 @
b1111111111111001 D
b1111111111111001 X
b0 (
b0 Q
b0 W
b1000 L
b10 1
b0 T
b10 9
b10 G
b10 J
b10 I
b1010 N
b1000 K
b10011000000010 0
b10011000000010 [
b111 +
b111 O
b111 Z
1!
#450000
0!
#455000
0A
b0 P
b0 %
b0 U
0>
b11 5
b11 :
b11 =
1#
b0 6
b0 B
b0 ?
b0 E
b0 F
b11 M
b0 )
b0 @
b0 D
b0 X
1/
b0 7
b0 ;
b0 H
03
b1001 L
b11 1
b0 S
b11 9
b1000 G
b11 J
b11 I
b1100 N
b1001 K
b1000000000000011 0
b1000000000000011 [
b1000 +
b1000 O
b1000 Z
1!
#460000
0!
#465000
b100 $
b100 V
b0 5
b0 :
b0 =
1&
1'
0/
b100 M
b100 L
b1111111111100000 1
b10 T
b10 S
b0 9
b0 G
b100000 J
b100000 I
b100100 N
b100 K
b10010100000 0
b10010100000 [
b11 +
b11 O
b11 Z
1!
#470000
0!
#475000
b101 M
b10 $
b10 V
b1000 7
b1000 ;
b1000 H
14
1&
0'
b101 L
b0 1
b100 S
b110 G
b0 J
b0 I
b101 N
b101 K
b110100010000000 0
b110100010000000 [
b100 +
b100 O
b100 Z
1!
#480000
0!
#485000
b110 M
b110 L
b1 S
b110 N
b110 K
b110001010000000 0
b110001010000000 [
b101 +
b101 O
b101 Z
1!
#490000
0!
